emploi_store/__init__.py
emploi_store/__init__.pyi
emploi_store/py.typed
python_emploi_store-0.10.2.dist-info/LICENSE.txt
python_emploi_store-0.10.2.dist-info/METADATA
python_emploi_store-0.10.2.dist-info/WHEEL
python_emploi_store-0.10.2.dist-info/top_level.txt
python_emploi_store-0.10.2.dist-info/RECORD
