Metadata-Version: 2.1
Name: python-emploi-store
Version: 0.10.2
Summary: Python client library for Pôle Emploi's "Emploi Store Dev".
Home-page: https://github.com/bayesimpact/python-emploi-store
Author: Pascal Corpet
Author-email: pascal@bayesimpact.org
License: The MIT License (MIT)
Download-URL: https://github.com/bayesimpact/python-emploi-store/tarball/0.10.2
Keywords: Pôle Emploi,France,emploi,OpenData
Platform: UNKNOWN
Requires-Dist: requests
Requires-Dist: six
Provides-Extra: dev
Requires-Dist: codecov ; extra == 'dev'
Requires-Dist: coverage ; extra == 'dev'
Requires-Dist: mock ; extra == 'dev'
Requires-Dist: nose ; extra == 'dev'
Requires-Dist: nose-watch ; extra == 'dev'
Requires-Dist: pylint ; extra == 'dev'
Requires-Dist: pylint-quotes ; extra == 'dev'
Requires-Dist: requests-mock ; extra == 'dev'
